LICENSE
MANIFEST.in
README.rst
pytest.ini
requirements.txt
setup.py
gq/__init__.py
gq/core.py
gq/expr.py
gq/missing.py
gq/pbar.py
gq.egg-info/PKG-INFO
gq.egg-info/SOURCES.txt
gq.egg-info/dependency_links.txt
gq.egg-info/top_level.txt
test/test_expr.py
test/test_gq.py