Metadata-Version: 1.1
Name: gq
Version: 0.0.3
Summary: a query-like selector for maf data
Home-page: http://github.com/ganow/gq/
Author: Yoshihiro Nagano
Author-email: y.nagano.92@gmail.com
License: MIT License
Platform: UNKNOWN
Classifier: Programming Language :: Python :: 2 :: Only
Classifier: License :: OSI Approved :: MIT License
